.bumpversion.cfg
.readthedocs.yaml
CONTRIBUTING.md
LICENSE
MANIFEST.in
Makefile
Pipfile
README.md
pyproject.toml
setup.py
columbia_discord_bot.egg-info/PKG-INFO
columbia_discord_bot.egg-info/SOURCES.txt
columbia_discord_bot.egg-info/dependency_links.txt
columbia_discord_bot.egg-info/requires.txt
columbia_discord_bot.egg-info/top_level.txt
docs/Makefile
docs/conf.py
docs/index.md
docs/make.bat
docs/_build/html/_static/imagesize.py
docs/_build/html/_static/py.py
docs/_build/html/_static/six.py
docs/_build/html/_static/Jinja2-3.1.2.dist-info/LICENSE.rst
docs/_build/html/_static/MarkupSafe-2.1.2.dist-info/LICENSE.rst
docs/_build/html/_static/_distutils_hack/__init__.py
docs/_build/html/_static/_distutils_hack/override.py
docs/_build/html/_static/_pytest/__init__.py
docs/_build/html/_static/_pytest/_argcomplete.py
docs/_build/html/_static/_pytest/_version.py
docs/_build/html/_static/_pytest/cacheprovider.py
docs/_build/html/_static/_pytest/capture.py
docs/_build/html/_static/_pytest/compat.py
docs/_build/html/_static/_pytest/debugging.py
docs/_build/html/_static/_pytest/deprecated.py
docs/_build/html/_static/_pytest/doctest.py
docs/_build/html/_static/_pytest/faulthandler.py
docs/_build/html/_static/_pytest/fixtures.py
docs/_build/html/_static/_pytest/freeze_support.py
docs/_build/html/_static/_pytest/helpconfig.py
docs/_build/html/_static/_pytest/hookspec.py
docs/_build/html/_static/_pytest/junitxml.py
docs/_build/html/_static/_pytest/legacypath.py
docs/_build/html/_static/_pytest/logging.py
docs/_build/html/_static/_pytest/main.py
docs/_build/html/_static/_pytest/monkeypatch.py
docs/_build/html/_static/_pytest/nodes.py
docs/_build/html/_static/_pytest/nose.py
docs/_build/html/_static/_pytest/outcomes.py
docs/_build/html/_static/_pytest/pastebin.py
docs/_build/html/_static/_pytest/pathlib.py
docs/_build/html/_static/_pytest/pytester.py
docs/_build/html/_static/_pytest/pytester_assertions.py
docs/_build/html/_static/_pytest/python.py
docs/_build/html/_static/_pytest/python_api.py
docs/_build/html/_static/_pytest/python_path.py
docs/_build/html/_static/_pytest/recwarn.py
docs/_build/html/_static/_pytest/reports.py
docs/_build/html/_static/_pytest/runner.py
docs/_build/html/_static/_pytest/scope.py
docs/_build/html/_static/_pytest/setuponly.py
docs/_build/html/_static/_pytest/setupplan.py
docs/_build/html/_static/idna-3.4.dist-info/LICENSE.md
docs/_build/html/_static/imagesize-1.4.1.dist-info/LICENSE.rst
docs/_build/html/_static/jinja2_time-0.2.0.dist-info/DESCRIPTION.rst
