Metadata-Version: 2.1
Name: columbia-discord-bot
Version: 0.2.1
Summary: A discord bot for Columbia University
Home-page: https://github.com/mw3071/columbia-discord-bot
Author: Matthew Wang
Author-email: Matthew Wang <mw3071@columbia.edu>
Maintainer: mw3071
Maintainer-email: mw3071@columbia.edu
License:                                  Apache License
Project-URL: repository, https://github.com/mw3071/columbia-discord-bot
Classifier: Development Status :: 2 - Pre-Alpha
Classifier: Programming Language :: Python :: Implementation :: CPython
Classifier: Programming Language :: Python :: Implementation :: PyPy
Classifier: Programming Language :: Python :: 3
Classifier: Programming Language :: Python :: 3.7
Classifier: Programming Language :: Python :: 3.8
Classifier: Programming Language :: Python :: 3.9
Classifier: Programming Language :: Python :: 3.10
Classifier: Programming Language :: Python :: 3.11
Requires-Python: >=3.7
Provides-Extra: develop
License-File: LICENSE
